intel-qs/build/lib/libiqs.so
intel-qs/build/lib/intelqs_py.cpython-37m-x86_64-linux-gnu.so
qublets.libs/libgomp-ce6cf6a9.so.1.0.0
qublets.libs/libiqs-3560124b.so
qublets/qints.py
qublets/qubit.py
qublets/rng.py
qublets/qpu.py
qublets/__init__.py
qublets/iqs.py
qublets/simulation.py
qublets-0.1.3.dist-info/METADATA
qublets-0.1.3.dist-info/WHEEL
qublets-0.1.3.dist-info/top_level.txt
qublets-0.1.3.dist-info/LICENSE
qublets-0.1.3.dist-info/RECORD
