Metadata-Version: 2.1
Name: qublets
Version: 0.1.3
Summary: A quantum computing library for the rest of us
Home-page: https://github.com/dyordan1/qublets
Author: Dobromir Yordanov
Author-email: dobri.domain@gmail.com
License: UNKNOWN
Platform: UNKNOWN
Requires-Python: >=3.6
License-File: LICENSE
